mrc2omezarr/__init__.py
mrc2omezarr/_version.py
mrc2omezarr/cli.py
mrc2omezarr/convert.py
mrc2omezarr/header.py
mrc2omezarr/proc.py
mrc2omezarr/read.py
mrc2omezarr/util.py
mrc2omezarr/write.py
mrc2omezarr-0.3.dist-info/METADATA
mrc2omezarr-0.3.dist-info/WHEEL
mrc2omezarr-0.3.dist-info/entry_points.txt
mrc2omezarr-0.3.dist-info/licenses/LICENSE
mrc2omezarr-0.3.dist-info/RECORD
