Metadata-Version: 2.3
Name: mrc2omezarr
Version: 0.3
Summary: Command line tool to convert MRC-files to OME-Zarr.
Project-URL: Repository, https://github.com/uermel/mrc2omezarr.git
Project-URL: Issues, https://github.com/uermel/mrc2omezarr/issues
Author-email: "Utz H. Ermel" <utz@ermel.me>
License: MIT License
License-File: LICENSE
Keywords: conversion,cryo-et,cryoet,mrc,ome,tomography,zarr
Classifier: Development Status :: 3 - Alpha
Classifier: License :: OSI Approved :: MIT License
Requires-Python: >=3.9
Requires-Dist: click
Requires-Dist: fsspec
Requires-Dist: mrcfile
Requires-Dist: numpy
Requires-Dist: ome-zarr
Requires-Dist: pydantic-ome-ngff
Requires-Dist: pydantic>2
Requires-Dist: zarr<3
Provides-Extra: dev
Requires-Dist: black; extra == 'dev'
Requires-Dist: ipython; extra == 'dev'
Requires-Dist: notebook; extra == 'dev'
Requires-Dist: pre-commit; extra == 'dev'
Requires-Dist: ruff; extra == 'dev'
